setup.py
django_hashed_url.egg-info/PKG-INFO
django_hashed_url.egg-info/SOURCES.txt
django_hashed_url.egg-info/dependency_links.txt
django_hashed_url.egg-info/requires.txt
django_hashed_url.egg-info/top_level.txt
hashed_url/__init__.py
hashed_url/decorators.py
hashed_url/models.py
hashed_url/tests.py
hashed_url/utilities.py
hashed_url/management/__init__.py
hashed_url/management/commands/__init__.py
hashed_url/management/commands/hashurl.py
hashed_url/templatetags/__init__.py
hashed_url/templatetags/hashedurl.py