Metadata-Version: 1.0
Name: django-hashed-url
Version: 0.1.1
Summary: Package for pre-authorising URLs using a hash parameter
Home-page: https://github.com/continuous/django-hashed-url
Author: Adam Charnock
Author-email: adam@playnice.ly
License: Apache Software License
Platform: UNKNOWN
Classifier: Development Status :: 4 - Beta
Classifier: Environment :: Web Environment
Classifier: Intended Audience :: Developers
Classifier: Natural Language :: English
Classifier: Programming Language :: Python :: 2.6
Classifier: Topic :: Security
Classifier: Framework :: Django
